CHANGELOG.rst
LICENSE.txt
MANIFEST.in
README.rst
VERSION.txt
setup.cfg
setup.py
globre/__init__.py
globre/test.py
globre.egg-info/PKG-INFO
globre.egg-info/SOURCES.txt
globre.egg-info/dependency_links.txt
globre.egg-info/requires.txt
globre.egg-info/top_level.txt
globre.egg-info/zip-safe