Metadata-Version: 1.1
Name: globre
Version: 0.1.2
Summary: A glob matching library, providing an interface similar to the "re" module.
Home-page: http://github.com/metagriffin/globre
Author: metagriffin
Author-email: mg.pypi@uberdev.org
License: GPLv3+
Keywords: python glob pattern matching regular expression
Platform: any
Classifier: Development Status :: 4 - Beta
Classifier: Intended Audience :: Developers
Classifier: Programming Language :: Python
Classifier: Operating System :: OS Independent
Classifier: Natural Language :: English
Classifier: License :: OSI Approved :: GNU General Public License v3 or later (GPLv3+)
